aurl/__init__.py
aurl/aftp.py
aurl/exceptions.py
aurl/fetch.py
aurl/get.py
aurl/get_dir.py
aurl/mirror.py
aurl/py.typed
aurl/runcmd.py
aurl/search.py
aurl/serve.py
aurl/subst.py
aurl/taskmgr.py
aurl/template.py
aurl/urls.py
aurl_aurl-2.4.0.dist-info/LICENSE.txt
aurl_aurl-2.4.0.dist-info/METADATA
aurl_aurl-2.4.0.dist-info/WHEEL
aurl_aurl-2.4.0.dist-info/entry_points.txt
aurl_aurl-2.4.0.dist-info/RECORD
