Metadata-Version: 2.3
Name: aurl-aurl
Version: 2.4.0
Summary: A package for maintaining a download mirror / cache and splicing URLs into file templates.
License: BSD-3-Clause
Author: David M. Rogers
Author-email: predictivestatmech@gmail.com>
Requires-Python: >=3.9,<4.0
Classifier: Programming Language :: Python
Classifier: Development Status :: 4 - Beta
Classifier: Framework :: AsyncIO
Provides-Extra: certified
Requires-Dist: aiofiles (>=24.1.0,<25.0)
Requires-Dist: aiohttp (>=3.8.5,<4.0)
Requires-Dist: certified (>=0.10,<2.0) ; extra == "certified"
Requires-Dist: typer (>=0.9,<1.0)
Project-URL: Repository, https://github.com/frobnitzem/aurl
